uploadoss/__init__.py
uploadoss/uploadoss.py
uploadoss/uploadoss_ora.py
uploadoss-0.4.6.dist-info/licenses/LICENSE.txt
uploadoss-0.4.6.dist-info/METADATA
uploadoss-0.4.6.dist-info/WHEEL
uploadoss-0.4.6.dist-info/top_level.txt
uploadoss-0.4.6.dist-info/RECORD
