Metadata-Version: 2.4
Name: uploadoss
Version: 0.4.6
Summary: Uploadoss is the general module of uploading database data and local files to the Alibaba Cloud OSS
Author: Binghe
Project-URL: Source, https://github.com/binghexmo/uploadoss/
License-File: LICENSE.txt
Requires-Dist: oss2
Requires-Dist: pandas
Requires-Dist: pymysql
Requires-Dist: configparser
Requires-Dist: oracledb
Dynamic: author
Dynamic: description
Dynamic: description-content-type
Dynamic: license-file
Dynamic: project-url
Dynamic: requires-dist
Dynamic: summary
